cookdata_convert/__init__.py
cookdata_convert/__main__.py
cookdata_convert/cookDataToSbyml.py
cookdata_convert/cookDataToYml.py
cookdata_convert/data/lookups.json
cookdata_convert-0.0.4.dist-info/METADATA
cookdata_convert-0.0.4.dist-info/WHEEL
cookdata_convert-0.0.4.dist-info/entry_points.txt
cookdata_convert-0.0.4.dist-info/top_level.txt
cookdata_convert-0.0.4.dist-info/RECORD
