Metadata-Version: 2.1
Name: cookdata-convert
Version: 0.0.4
Summary: CookData converter for LoZ:BotW
Home-page: https://github.com/GingerAvalanche/cookdata_convert
Author: Ginger
Author-email: chodness@gmail.com
License: UNKNOWN
Platform: UNKNOWN
Classifier: Programming Language :: Python :: 3.7
Classifier: License :: OSI Approved :: GNU Affero General Public License v3 or later (AGPLv3+)
Classifier: Operating System :: OS Independent
Classifier: Development Status :: 3 - Alpha
Requires-Python: >=3.7.4
Requires-Dist: oead (>=0.11.2)
